pyvfw/__init__.py
pyvfw-1.0.1.dist-info/LICENSE
pyvfw-1.0.1.dist-info/METADATA
pyvfw-1.0.1.dist-info/WHEEL
pyvfw-1.0.1.dist-info/top_level.txt
pyvfw-1.0.1.dist-info/RECORD
