Metadata-Version: 2.1
Name: pyvfw
Version: 1.0.1
Summary: A small Python package to change, increase, mute, or unmute the volume on Windows.
Author: TerinalTech
License: Copyright (c) 2018 The Python Packaging Authority
Project-URL: Homepage, https://github.com/TerinalTech/pyvfw
Project-URL: Issues, https://github.com/TerinalTech/pyvfw/issues
Keywords: pyvfw,volume for windows,windows,windows volume
Classifier: Programming Language :: Python :: 3
Classifier: License :: OSI Approved :: MIT License
Classifier: Operating System :: Microsoft :: Windows
Requires-Python: >=3.6
License-File: LICENSE
Requires-Dist: pycaw
Requires-Dist: comtypes
